{
  "_id": "Zl9i4QPHcgr44ZaE",
  "name": "Crypto Chips",
  "type": "cyberware",
  "img": "icons/svg/biohazard.svg",
  "system": {
    "flavor": "Randomly generated substitution word code 600 per",
    "notes": "<p>USER-VERIFIED: 600eb per set of two; sets of 2/4/6/8 (each set a unique word-substitution code, covert speech). [OCR showed 'SOOeb' — S was a 6.] | [Audit row +4 — Chromebook 3 p.37]</p>",
    "cost": 600,
    "weight": 0,
    "equipped": false,
    "source": "Chromebook 3 pg.37",
    "lastOwnerId": "",
    "surgCode": "N",
    "humanityCost": "0",
    "cyberwareType": "CHIPWARE",
    "cyberwareSubtype": "OPTION",
    "abbrev": "",
    "humanityLoss": 0,
    "MountZone": "",
    "EffectMode": "Permanent",
    "EffectActive": false,
    "Module": {},
    "CyberBodyType": {},
    "CyberWorkType": {
      "Type": "Chip",
      "Types": [
        "Chip"
      ],
      "ChipSkills": {},
      "ChipActive": false
    },
    "slots": 0,
    "spaces": 0,
    "cwTypeLabel": "",
    "cwSubtypeLabel": "",
    "effectTypes": [
      "None"
    ]
  },
  "effects": [],
  "folder": null,
  "sort": 13000000,
  "ownership": {
    "default": 0
  },
  "flags": {
    "cp2020-augmented": {
      "importCategory": "chipware",
      "importReview": {
        "level": "clean",
        "weightSkimNotReviewed": true,
        "ledger": "SUPPLEMENT-IMPORT-CHECKLIST",
        "dirty": false
      }
    }
  },
  "_stats": {},
  "_key": "!items!Zl9i4QPHcgr44ZaE"
}
