{
  "_id": "EGnbXGoZos0Lk1Go",
  "name": "Crypto Chips (set of 2)",
  "type": "cyberware",
  "img": "icons/svg/biohazard.svg",
  "system": {
    "flavor": "",
    "notes": "<p>USER-VERIFIED: 600eb per set of two; sets of 2/4/6/8 (each set a unique word-substitution code, covert speech). [OCR showed 'SOOeb' — S was a 6.] | [Audit row +4 — Chromebook 3 p.37]</p>",
    "cost": 600,
    "weight": 0,
    "equipped": false,
    "source": "Chromebook 3 p.37",
    "lastOwnerId": "",
    "surgCode": "",
    "humanityCost": "",
    "cyberwareType": "",
    "cyberwareSubtype": "",
    "abbrev": "",
    "humanityLoss": 0,
    "MountZone": "",
    "EffectMode": "Permanent",
    "EffectActive": false,
    "Module": {},
    "CyberBodyType": {},
    "CyberWorkType": {},
    "slots": 0,
    "spaces": 0,
    "cwTypeLabel": "",
    "cwSubtypeLabel": "",
    "effectTypes": [
      "None"
    ]
  },
  "effects": [],
  "folder": null,
  "sort": 10100000,
  "ownership": {
    "default": 0
  },
  "flags": {
    "cp2020-augmented": {
      "auditWalk": {
        "row": "+4",
        "ledger": "CP2020-Checklists 05JUL26 Lee",
        "book": "Chromebook 3",
        "page": 37
      },
      "manufacturer": "Direct Dataware",
      "importCategory": "cyberware",
      "importReview": {
        "level": "user-verified",
        "weightSkimNotReviewed": true,
        "ledger": "AUDIT-WALK-2026-07",
        "dirty": false
      }
    }
  },
  "_stats": {},
  "_key": "!items!EGnbXGoZos0Lk1Go"
}
